scrapew/__init__.py
scrapew/client.py
scrapew_python_sdk-1.0.0.dist-info/METADATA
scrapew_python_sdk-1.0.0.dist-info/WHEEL
scrapew_python_sdk-1.0.0.dist-info/top_level.txt
scrapew_python_sdk-1.0.0.dist-info/RECORD
