Metadata-Version: 2.1
Name: scrapew-python-sdk
Version: 1.0.0
Summary: Get data from every web page as structured
Home-page: https://github.com/scrapew/scrapew-python-sdk
Author: Scrapew
Author-email: barakcin.baran@gmail.com
License: MIT
Platform: UNKNOWN
Classifier: License :: OSI Approved :: MIT License
Classifier: Programming Language :: Python :: 3
Classifier: Programming Language :: Python :: 3.7
Requires-Dist: requests
Requires-Dist: furl
